tankersdk/__init__.py
tankersdk/crypto/__init__.py
tankersdk/test/__init__.py
tankersdk/test/conftest.py
tankersdk/test/helpers.py
tankersdk/test/test_crypto.py
tankersdk/test/test_user_token.py
tankersdk/usertoken/__init__.py
tankersdk_user_token-0.3.dist-info/METADATA
tankersdk_user_token-0.3.dist-info/WHEEL
tankersdk_user_token-0.3.dist-info/top_level.txt
tankersdk_user_token-0.3.dist-info/RECORD
