Metadata-Version: 2.1
Name: tankersdk-user-token
Version: 0.3
Summary: Tanker user token library
Home-page: https://github.com/TankerHQ/user-token-python
Author: Kontrol SAS
License: UNKNOWN
Platform: UNKNOWN
Classifier: Programming Language :: Python :: 2.7
Classifier: Programming Language :: Python :: 3.4
Classifier: Programming Language :: Python :: 3.5
Classifier: Programming Language :: Python :: 3.6
Classifier: Programming Language :: Python :: 3.7
Requires-Dist: PyNaCl
Provides-Extra: dev
Requires-Dist: pytest ; extra == 'dev'
